pcpi/__init__.py
pcpi/_cna_session.py
pcpi/_cspm_session.py
pcpi/_onprem_cwp_session.py
pcpi/_saas_cwp_session.py
pcpi/_session_base.py
pcpi/_session_types.py
pcpi/onprem_session_manager.py
pcpi/saas_session_manager.py
pcpi/session_loader.py
pcpi-1.0.1.dist-info/METADATA
pcpi-1.0.1.dist-info/WHEEL
pcpi-1.0.1.dist-info/licenses/LICENSE
pcpi-1.0.1.dist-info/RECORD
