Metadata-Version: 2.4
Name: pcpi
Version: 1.0.1
Summary: Python Package for making API calls to the Prisma Cloud API using best practices.
Project-URL: Homepage, https://github.com/PaloAltoNetworks/pc-python-integration
Project-URL: Bug Tracker, https://github.com/PaloAltoNetworks/pc-python-integration/issues
Author-email: Adam Hamilton-Sutherland <ahamiltonsut@paloaltonetworks.com>
License: ISC License
License-File: LICENSE
Classifier: Development Status :: 4 - Beta
Classifier: License :: OSI Approved :: ISC License (ISCL)
Classifier: Operating System :: OS Independent
Classifier: Programming Language :: Python :: 3
Requires-Python: >=3.7
Requires-Dist: pyyaml~=6.0
Requires-Dist: requests<3
